artd/__init__.py
artd/asgi.py
artd/settings.py
artd/urls.py
artd/wsgi.py
artd_location/__init__.py
artd_location/admin.py
artd_location/apps.py
artd_location/models.py
artd_location/signals.py
artd_location/data/__init__.py
artd_location/data/chile_cities.py
artd_location/data/chile_regions.py
artd_location/data/cities.py
artd_location/data/countries.py
artd_location/data/currencies.py
artd_location/data/languages.py
artd_location/data/regions.py
artd_location/generators/__init__.py
artd_location/generators/generators.py
artd_location/locale/en/LC_MESSAGES/django.po
artd_location/locale/es/LC_MESSAGES/django.po
artd_location/management/__init__.py
artd_location/management/commands/__init__.py
artd_location/management/commands/create_chile_cities.py
artd_location/management/commands/create_chile_regions.py
artd_location/management/commands/create_colombian_cities.py
artd_location/management/commands/create_colombian_regions.py
artd_location/management/commands/create_countries.py
artd_location/management/commands/create_currencies.py
artd_location/migrations/0001_initial.py
artd_location/migrations/0002_alter_city_created_at_alter_city_status_and_more.py
artd_location/migrations/0003_region_code.py
artd_location/migrations/0004_currency.py
artd_location/migrations/0005_rename_simbol_currency_symbol.py
artd_location/migrations/__init__.py
artd_location-1.0.8.dist-info/LICENSE
artd_location-1.0.8.dist-info/METADATA
artd_location-1.0.8.dist-info/WHEEL
artd_location-1.0.8.dist-info/top_level.txt
artd_location-1.0.8.dist-info/RECORD
